{"ObjectStates":[{"Name":"DeckCustom","ContainedObjects":[{"CardID":100,"Name":"Card","Nickname":"Liliana, Dreadhorde General","Transform":{"posX":0,"posY":0,"posZ":0,"rotX":0,"rotY":180,"rotZ":180,"scaleX":1,"scaleY":1,"scaleZ":1}},{"CardID":200,"Name":"Card","Nickname":"Wall of Denial","Transform":{"posX":0,"posY":0,"posZ":0,"rotX":0,"rotY":180,"rotZ":180,"scaleX":1,"scaleY":1,"scaleZ":1}},{"CardID":300,"Name":"Card","Nickname":"Umezawa's Jitte","Transform":{"posX":0,"posY":0,"posZ":0,"rotX":0,"rotY":180,"rotZ":180,"scaleX":1,"scaleY":1,"scaleZ":1}},{"CardID":400,"Name":"Card","Nickname":"Perilous Myr","Transform":{"posX":0,"posY":0,"posZ":0,"rotX":0,"rotY":180,"rotZ":180,"scaleX":1,"scaleY":1,"scaleZ":1}},{"CardID":500,"Name":"Card","Nickname":"Bituminous Blast","Transform":{"posX":0,"posY":0,"posZ":0,"rotX":0,"rotY":180,"rotZ":180,"scaleX":1,"scaleY":1,"scaleZ":1}},{"CardID":600,"Name":"Card","Nickname":"Lightning Bolt","Transform":{"posX":0,"posY":0,"posZ":0,"rotX":0,"rotY":180,"rotZ":180,"scaleX":1,"scaleY":1,"scaleZ":1}},{"CardID":700,"Name":"Card","Nickname":"Mind Stone","Transform":{"posX":0,"posY":0,"posZ":0,"rotX":0,"rotY":180,"rotZ":180,"scaleX":1,"scaleY":1,"scaleZ":1}},{"CardID":800,"Name":"Card","Nickname":"Myr Battlesphere","Transform":{"posX":0,"posY":0,"posZ":0,"rotX":0,"rotY":180,"rotZ":180,"scaleX":1,"scaleY":1,"scaleZ":1}},{"CardID":900,"Name":"Card","Nickname":"Revoke Existence","Transform":{"posX":0,"posY":0,"posZ":0,"rotX":0,"rotY":180,"rotZ":180,"scaleX":1,"scaleY":1,"scaleZ":1}},{"CardID":1000,"Name":"Card","Nickname":"Abrupt Decay","Transform":{"posX":0,"posY":0,"posZ":0,"rotX":0,"rotY":180,"rotZ":180,"scaleX":1,"scaleY":1,"scaleZ":1}},{"CardID":1100,"Name":"Card","Nickname":"Sun Titan","Transform":{"posX":0,"posY":0,"posZ":0,"rotX":0,"rotY":180,"rotZ":180,"scaleX":1,"scaleY":1,"scaleZ":1}}],"DeckIDs":[100,200,300,400,500,600,700,800,900,1000,1100],"CustomDeck":{"1":{"FaceURL":"https://s3.amazonaws.com/frogtown.cards.hq/06bcf9ac-f0f7-405b-960b-ebf15b2640a7.jpg","BackURL":"https://customcards.s3.us-east-2.amazonaws.com/card_back.jpg","NumHeight":1,"NumWidth":1,"BackIsHidden":true},"2":{"FaceURL":"https://s3.amazonaws.com/frogtown.cards.hq/0cd95bba-0c3d-4f2c-94ea-bbd3f396292c.jpg","BackURL":"https://customcards.s3.us-east-2.amazonaws.com/card_back.jpg","NumHeight":1,"NumWidth":1,"BackIsHidden":true},"3":{"FaceURL":"https://s3.amazonaws.com/frogtown.cards.hq/31304ee9-5b0a-49f5-86ba-bbfc7fe60658.jpg","BackURL":"https://customcards.s3.us-east-2.amazonaws.com/card_back.jpg","NumHeight":1,"NumWidth":1,"BackIsHidden":true},"4":{"FaceURL":"https://s3.amazonaws.com/frogtown.cards.hq/4b942605-eb4a-452d-9b07-a4f912f96958.jpg","BackURL":"https://customcards.s3.us-east-2.amazonaws.com/card_back.jpg","NumHeight":1,"NumWidth":1,"BackIsHidden":true},"5":{"FaceURL":"https://s3.amazonaws.com/frogtown.cards.hq/4e72d6ed-535a-4ea1-b3c7-bd5d792290b2.jpg","BackURL":"https://customcards.s3.us-east-2.amazonaws.com/card_back.jpg","NumHeight":1,"NumWidth":1,"BackIsHidden":true},"6":{"FaceURL":"https://s3.amazonaws.com/frogtown.cards.hq/6fb94c1b-8002-4d79-add0-c4dfef9019ee.jpg","BackURL":"https://customcards.s3.us-east-2.amazonaws.com/card_back.jpg","NumHeight":1,"NumWidth":1,"BackIsHidden":true},"7":{"FaceURL":"https://s3.amazonaws.com/frogtown.cards.hq/831584ac-bb81-4f0a-bd36-282bd9a2a89e.jpg","BackURL":"https://customcards.s3.us-east-2.amazonaws.com/card_back.jpg","NumHeight":1,"NumWidth":1,"BackIsHidden":true},"8":{"FaceURL":"https://s3.amazonaws.com/frogtown.cards.hq/88d33b63-9a49-4c67-9932-270997f6625b.jpg","BackURL":"https://customcards.s3.us-east-2.amazonaws.com/card_back.jpg","NumHeight":1,"NumWidth":1,"BackIsHidden":true},"9":{"FaceURL":"https://s3.amazonaws.com/frogtown.cards.hq/9dbb9f86-f487-44b1-815f-30d87868b531.jpg","BackURL":"https://customcards.s3.us-east-2.amazonaws.com/card_back.jpg","NumHeight":1,"NumWidth":1,"BackIsHidden":true},"10":{"FaceURL":"https://s3.amazonaws.com/frogtown.cards.hq/a8e328c6-3a84-49cf-a1a3-1d1e5373d274.jpg","BackURL":"https://customcards.s3.us-east-2.amazonaws.com/card_back.jpg","NumHeight":1,"NumWidth":1,"BackIsHidden":true},"11":{"FaceURL":"https://s3.amazonaws.com/frogtown.cards.hq/cd7a20a2-4489-42c7-9a39-4e2de95c77e2.jpg","BackURL":"https://customcards.s3.us-east-2.amazonaws.com/card_back.jpg","NumHeight":1,"NumWidth":1,"BackIsHidden":true}},"Transform":{"posX":0,"posY":1,"posZ":0,"rotX":0,"rotY":180,"rotZ":180,"scaleX":1,"scaleY":1,"scaleZ":1}},{"Name":"DeckCustom","ContainedObjects":[{"CardID":100,"Name":"Card","Nickname":"Zombie","Transform":{"posX":0,"posY":0,"posZ":0,"rotX":0,"rotY":180,"rotZ":180,"scaleX":1,"scaleY":1,"scaleZ":1}},{"CardID":200,"Name":"Card","Nickname":"Myr","Transform":{"posX":0,"posY":0,"posZ":0,"rotX":0,"rotY":180,"rotZ":180,"scaleX":1,"scaleY":1,"scaleZ":1}}],"DeckIDs":[100,200],"CustomDeck":{"1":{"FaceURL":"https://s3.amazonaws.com/frogtown.cards.hq/0397aa00-6d82-47d9-bc30-072b722c8b71.jpg","BackURL":"https://customcards.s3.us-east-2.amazonaws.com/card_back.jpg","NumHeight":1,"NumWidth":1,"BackIsHidden":true},"2":{"FaceURL":"https://s3.amazonaws.com/frogtown.cards.hq/182308b3-86e0-46d8-9104-95576a3d3921.jpg","BackURL":"https://customcards.s3.us-east-2.amazonaws.com/card_back.jpg","NumHeight":1,"NumWidth":1,"BackIsHidden":true}},"Transform":{"posX":2.2,"posY":1,"posZ":0,"rotX":0,"rotY":180,"rotZ":0,"scaleX":1,"scaleY":1,"scaleZ":1}}]}